widdy/__init__.py
widdy/__main__.py
widdy/demos.py
widdy/styles.py
widdy/widgets.py
widdy/examples/__init__.py
widdy/examples/chuck.py
widdy/examples/counter.py
widdy-0.2.13.dist-info/LICENSE.txt
widdy-0.2.13.dist-info/METADATA
widdy-0.2.13.dist-info/WHEEL
widdy-0.2.13.dist-info/entry_points.txt
widdy-0.2.13.dist-info/top_level.txt
widdy-0.2.13.dist-info/RECORD
