Metadata-Version: 2.1
Name: widdy
Version: 0.2.13
Summary: urwid wrapper for rapid shell-ui prototyping
Home-page: https://github.com/ubunatic/widdy
Author: Uwe Jugel
Author-email: uwe.jugel@gmail.com
License: MIT
Project-URL: Documentation, https://github.com/ubunatic/widdy
Project-URL: Bug Reports, https://github.com/ubunatic/widdy/issues
Project-URL: Funding, https://github.com/ubunatic/widdy
Project-URL: Say Thanks!, https://saythanks.io/to/ubunatic
Project-URL: Source, https://github.com/ubunatic/widdy
Keywords: urwid,prototyping,widgets,ohlc,ui,apps,console
Classifier: Development Status :: 3 - Alpha
Classifier: Intended Audience :: Developers
Classifier: License :: OSI Approved :: MIT License
Classifier: Programming Language :: Python :: 3
Classifier: Environment :: Console :: Curses
Classifier: Topic :: Software Development :: Widget Sets
Classifier: Topic :: Software Development :: Libraries :: Application Frameworks
Requires-Python: >=3.5
License-File: LICENSE.txt
Requires-Dist: urwid
Requires-Dist: requests
Requires-Dist: typing
Provides-Extra: dev
Requires-Dist: pytest ; extra == 'dev'
Requires-Dist: flake8 ; extra == 'dev'
Requires-Dist: twine ; extra == 'dev'
